simple_json_yaml_toml_converter/__init__.py
simple_json_yaml_toml_converter/cli.py
simple_json_yaml_toml_converter-0.1.1.dist-info/entry_points.txt
simple_json_yaml_toml_converter-0.1.1.dist-info/WHEEL
simple_json_yaml_toml_converter-0.1.1.dist-info/METADATA
simple_json_yaml_toml_converter-0.1.1.dist-info/RECORD
