Metadata-Version: 2.1
Name: simple-json-yaml-toml-converter
Version: 0.1.1
Summary: Simple json/yaml/toml CLI converter.
Home-page: https://github.com/0djentd/simple-json-yaml-toml-converter
Author: 0djentd
Requires-Python: >=3.10,<4.0
Classifier: Programming Language :: Python :: 3
Classifier: Programming Language :: Python :: 3.10
Requires-Dist: PyYAML (>=6.0,<7.0)
Requires-Dist: click (>=8.1.3,<9.0.0)
Requires-Dist: toml (>=0.10.2,<0.11.0)
Project-URL: Repository, https://github.com/0djentd/simple-json-yaml-toml-converter
